<?xml version="1.0" encoding="UTF-8"?>
<teamworks>
    <process id="1.02cc1aee-431d-4aa0-87fc-b046b07cdbeb" name="Get MIME Types NV Pair">
        <lastModified>1528548874159</lastModified>
        <lastModifiedBy>asansanwal</lastModifiedBy>
        <processId>1.02cc1aee-431d-4aa0-87fc-b046b07cdbeb</processId>
        <image isNull="true" />
        <tabGroup isNull="true" />
        <startingProcessItemId>2025.2abd430b-a057-4be0-96b1-638b80cb25ea</startingProcessItemId>
        <isRootProcess>false</isRootProcess>
        <processType>12</processType>
        <isErrorHandlerEnabled>false</isErrorHandlerEnabled>
        <errorHandlerItemId isNull="true" />
        <isLoggingVariables>false</isLoggingVariables>
        <isTransactional>false</isTransactional>
        <processTimingLevel isNull="true" />
        <participantRef isNull="true" />
        <exposedType>0</exposedType>
        <isTrackingEnabled>true</isTrackingEnabled>
        <xmlData isNull="true" />
        <cachingType>true</cachingType>
        <itemLabel isNull="true" />
        <cacheLength>43200</cacheLength>
        <mobileReady>false</mobileReady>
        <sboSyncEnabled>true</sboSyncEnabled>
        <externalId isNull="true" />
        <isSecured>true</isSecured>
        <isAjaxExposed>true</isAjaxExposed>
        <description isNull="true" />
        <guid>885e415b-02ad-4bd2-b9c9-55e6c2384731</guid>
        <versionId>0162a924-5cfd-43ca-8cc6-238ac44a1d37</versionId>
        <dependencySummary>&lt;dependencySummary id="c7fe7f66-df20-4cef-af55-19e6ccced82d" /&gt;</dependencySummary>
        <jsonData isNull="true" />
        <field1 isNull="true" />
        <field2 isNull="true" />
        <field3>0</field3>
        <field4 isNull="true" />
        <field5>false</field5>
        <clobField1 isNull="true" />
        <blobField1 isNull="true" />
        <processParameter name="data">
            <lastModified isNull="true" />
            <lastModifiedBy isNull="true" />
            <processParameterId>2055.144c3294-0c32-4609-a4df-e78e0bb91187</processParameterId>
            <processId>1.02cc1aee-431d-4aa0-87fc-b046b07cdbeb</processId>
            <parameterType>1</parameterType>
            <isArrayOf>false</isArrayOf>
            <classId>3eead070-014c-46ed-b858-fe3e6d6b248e/12.c09c9b6e-aabd-4897-bef2-ed61db106297</classId>
            <seq>1</seq>
            <hasDefault>false</hasDefault>
            <defaultValue isNull="true" />
            <isLocked>false</isLocked>
            <description isNull="true" />
            <guid>a4ac89d2-e7f5-4c5a-b134-2c9179578e8a</guid>
            <versionId>5369ce6e-1bac-471b-81cc-c0e645d348ef</versionId>
        </processParameter>
        <processParameter name="results">
            <lastModified isNull="true" />
            <lastModifiedBy isNull="true" />
            <processParameterId>2055.ab426bca-cbe8-41d0-ac77-9812fb594171</processParameterId>
            <processId>1.02cc1aee-431d-4aa0-87fc-b046b07cdbeb</processId>
            <parameterType>2</parameterType>
            <isArrayOf>true</isArrayOf>
            <classId>3eead070-014c-46ed-b858-fe3e6d6b248e/12.c09c9b6e-aabd-4897-bef2-ed61db106297</classId>
            <seq>2</seq>
            <hasDefault>false</hasDefault>
            <defaultValue isNull="true" />
            <isLocked>false</isLocked>
            <description isNull="true" />
            <guid>b11d6cfb-af38-4d8c-b608-9c98cdf096a7</guid>
            <versionId>92316c70-8ad6-4f85-bbf9-5b18fd0bf2e1</versionId>
        </processParameter>
        <processVariable name="InstanceSummary">
            <lastModified isNull="true" />
            <lastModifiedBy isNull="true" />
            <processVariableId>2056.98677004-e7d5-435f-941a-2a42e21d26fa</processVariableId>
            <description isNull="true" />
            <processId>1.02cc1aee-431d-4aa0-87fc-b046b07cdbeb</processId>
            <namespace>2</namespace>
            <seq>1</seq>
            <isArrayOf>true</isArrayOf>
            <isTransient>false</isTransient>
            <classId>/12.ae08caf5-4a15-4f12-a99e-d44923fd7975</classId>
            <hasDefault>true</hasDefault>
            <defaultValue>var autoObject = new tw.object.listOf.AppNameValue();
autoObject[0] = new tw.object.AppNameValue();
autoObject</defaultValue>
            <guid>12cea89e-4c3d-4660-af99-5f2e3c06df07</guid>
            <versionId>842a9709-82a5-4d5a-8717-b54f4c92dd86</versionId>
        </processVariable>
        <processVariable name="sqlParameters">
            <lastModified isNull="true" />
            <lastModifiedBy isNull="true" />
            <processVariableId>2056.129df22a-9b8a-4df4-947e-ec4bfe936372</processVariableId>
            <description isNull="true" />
            <processId>1.02cc1aee-431d-4aa0-87fc-b046b07cdbeb</processId>
            <namespace>2</namespace>
            <seq>2</seq>
            <isArrayOf>true</isArrayOf>
            <isTransient>false</isTransient>
            <classId>3eead070-014c-46ed-b858-fe3e6d6b248e/12.f453f500-ca4e-4264-a371-72c1892e8b7c</classId>
            <hasDefault>true</hasDefault>
            <defaultValue>var autoObject = new tw.object.listOf.toolkit.TWSYS.SQLParameter();
autoObject</defaultValue>
            <guid>2ea7765e-dad1-40b3-b134-68c33a12e2b4</guid>
            <versionId>5d95a23c-5700-4bcd-90c1-f5b6959ad5f2</versionId>
        </processVariable>
        <processVariable name="jndiName">
            <lastModified isNull="true" />
            <lastModifiedBy isNull="true" />
            <processVariableId>2056.70eaf1a4-9974-4a7c-af16-c40c689b93b8</processVariableId>
            <description isNull="true" />
            <processId>1.02cc1aee-431d-4aa0-87fc-b046b07cdbeb</processId>
            <namespace>2</namespace>
            <seq>3</seq>
            <isArrayOf>false</isArrayOf>
            <isTransient>false</isTransient>
            <classId>3eead070-014c-46ed-b858-fe3e6d6b248e/12.db884a3c-c533-44b7-bb2d-47bec8ad4022</classId>
            <hasDefault>true</hasDefault>
            <defaultValue>String(tw.env.ProcessServerDBJNDINAME)	</defaultValue>
            <guid>59a8d23e-547e-4c68-9921-3739f2079671</guid>
            <versionId>29aebd0b-7189-4572-aecf-477710334b95</versionId>
        </processVariable>
        <processVariable name="instancesStatuses">
            <lastModified isNull="true" />
            <lastModifiedBy isNull="true" />
            <processVariableId>2056.bebb2dae-a3f9-484a-890e-f7d6d3808410</processVariableId>
            <description isNull="true" />
            <processId>1.02cc1aee-431d-4aa0-87fc-b046b07cdbeb</processId>
            <namespace>2</namespace>
            <seq>4</seq>
            <isArrayOf>true</isArrayOf>
            <isTransient>false</isTransient>
            <classId>3eead070-014c-46ed-b858-fe3e6d6b248e/12.d2e5a15a-ea53-4793-9e93-29af5bd80b13</classId>
            <hasDefault>true</hasDefault>
            <defaultValue>var autoObject = new tw.object.listOf.toolkit.TWSYS.NameValuePair();
autoObject[0] = new tw.object.toolkit.TWSYS.NameValuePair();
autoObject[0].name = "Active";
autoObject[0].value = "1";
autoObject[1] = new tw.object.toolkit.TWSYS.NameValuePair();&#xD;
autoObject[1].name = "Completed";&#xD;
autoObject[1].value = "2";&#xD;
autoObject[2] = new tw.object.toolkit.TWSYS.NameValuePair();&#xD;
autoObject[2].name = "Failed";&#xD;
autoObject[2].value = "3";&#xD;
autoObject[3] = new tw.object.toolkit.TWSYS.NameValuePair();&#xD;
autoObject[3].name = "Terminated";&#xD;
autoObject[3].value = "4";&#xD;
autoObject[4] = new tw.object.toolkit.TWSYS.NameValuePair();&#xD;
autoObject[4].name = "Did_not_Start";&#xD;
autoObject[4].value = "5";&#xD;
autoObject[5] = new tw.object.toolkit.TWSYS.NameValuePair();&#xD;
autoObject[5].name = "Suspended";&#xD;
autoObject[5].value = "6";&#xD;
autoObject&#xD;
&#xD;
/*&#xD;
1 - The Process instance is currently active &#xD;
2 - The Process instance has completed or Finished &#xD;
3 - The Process instance has failed due error in execution&#xD;
4 - The Process instance has been terminated(abort) &#xD;
5 - The Process instance could not Start &#xD;
6 - The Process instance was suspended &#xD;
*/</defaultValue>
            <guid>d0e153b6-60e2-4e74-9314-e6cf2adb69f5</guid>
            <versionId>2537bbf5-752a-4e7e-90ec-544a66ca8ad1</versionId>
        </processVariable>
        <processVariable name="sqlStatement">
            <lastModified isNull="true" />
            <lastModifiedBy isNull="true" />
            <processVariableId>2056.404f732d-baa5-4e9c-abd9-a1c517889552</processVariableId>
            <description isNull="true" />
            <processId>1.02cc1aee-431d-4aa0-87fc-b046b07cdbeb</processId>
            <namespace>2</namespace>
            <seq>5</seq>
            <isArrayOf>false</isArrayOf>
            <isTransient>false</isTransient>
            <classId>3eead070-014c-46ed-b858-fe3e6d6b248e/12.db884a3c-c533-44b7-bb2d-47bec8ad4022</classId>
            <hasDefault>true</hasDefault>
            <defaultValue>""</defaultValue>
            <guid>c4f6e7e6-f27e-4070-b825-7b5935bfdbb9</guid>
            <versionId>3699ef39-474a-46ac-a41b-ac0553499dcf</versionId>
        </processVariable>
        <processVariable name="dataSeriesP">
            <lastModified isNull="true" />
            <lastModifiedBy isNull="true" />
            <processVariableId>2056.fddf5aa2-cc79-40f8-80c6-c288a0b4f39f</processVariableId>
            <description isNull="true" />
            <processId>1.02cc1aee-431d-4aa0-87fc-b046b07cdbeb</processId>
            <namespace>2</namespace>
            <seq>6</seq>
            <isArrayOf>true</isArrayOf>
            <isTransient>false</isTransient>
            <classId>1486ffce-93b8-4f98-862d-48b380e1a24f/12.63a604e8-e026-4605-aae1-272b67822cc7</classId>
            <hasDefault>true</hasDefault>
            <defaultValue>var autoObject = new tw.object.listOf.toolkit.SYSBPMUI.DataSeries();
autoObject[0] = new tw.object.toolkit.SYSBPMUI.DataSeries();
autoObject[0].seriesName = "All Applications";
autoObject[0].dataPoints = new tw.object.listOf.toolkit.SYSBPMUI.DataPoint();
autoObject[0].dataPoints[0] = new tw.object.toolkit.SYSBPMUI.DataPoint();
autoObject[0].dataPoints[0].value = 0.0;
autoObject[0].dataPoints[0].label = "";
autoObject</defaultValue>
            <guid>8f030e59-54bc-4299-8a16-0e77a7c76813</guid>
            <versionId>39f86d26-a76d-46eb-ac1f-796a06f17ba2</versionId>
        </processVariable>
        <item>
            <lastModified isNull="true" />
            <lastModifiedBy isNull="true" />
            <processItemId>2025.7e5b4f4f-7e16-4708-981d-1f94533cd4ee</processItemId>
            <processId>1.02cc1aee-431d-4aa0-87fc-b046b07cdbeb</processId>
            <name>SQL Execute Statement</name>
            <tWComponentName>SubProcess</tWComponentName>
            <tWComponentId>3012.ac245f99-a3c7-4780-8bc0-6c54df4102e0</tWComponentId>
            <isLogEnabled>false</isLogEnabled>
            <isTraceEnabled>false</isTraceEnabled>
            <traceCategory isNull="true" />
            <traceLevel isNull="true" />
            <traceMessage isNull="true" />
            <traceSymbolTable isNull="true" />
            <isExecutionContextTraced>false</isExecutionContextTraced>
            <saveExecutionContext>false</saveExecutionContext>
            <documentation isNull="true" />
            <isErrorHandlerEnabled>false</isErrorHandlerEnabled>
            <errorHandlerItemId isNull="true" />
            <guid>guid:1df100aa714bb228:7f4ddbfc:163e4948e80:-761c</guid>
            <versionId>1c800c95-7248-4dc9-ad8d-66e1b88bace1</versionId>
            <externalServiceRef isNull="true" />
            <externalServiceOp isNull="true" />
            <nodeColor isNull="true" />
            <layoutData x="330" y="56">
                <errorLink>
                    <controlPoints />
                    <showEndState>false</showEndState>
                    <showName>false</showName>
                </errorLink>
            </layoutData>
            <TWComponent>
                <lastModified isNull="true" />
                <lastModifiedBy isNull="true" />
                <subProcessId>3012.ac245f99-a3c7-4780-8bc0-6c54df4102e0</subProcessId>
                <attachedProcessRef>3eead070-014c-46ed-b858-fe3e6d6b248e/1.8ca80af0-a727-4b90-9e04-21b32cd0c65c</attachedProcessRef>
                <guid>ce72ee11-e870-4ba0-985c-ec1890ad073b</guid>
                <versionId>104ad1ee-15e9-4947-a8ce-e6bc23e0387e</versionId>
                <parameterMapping name="parameters">
                    <lastModified isNull="true" />
                    <lastModifiedBy isNull="true" />
                    <parameterMappingId>2054.fb766c7a-57c7-4c83-8b0b-e71469329b75</parameterMappingId>
                    <processParameterId>2055.8b3c4f58-67b5-49b0-8df4-bdb407fbe076</processParameterId>
                    <parameterMappingParentId>3012.ac245f99-a3c7-4780-8bc0-6c54df4102e0</parameterMappingParentId>
                    <useDefault>false</useDefault>
                    <value>tw.local.sqlParameters</value>
                    <classRef>/12.f453f500-ca4e-4264-a371-72c1892e8b7c</classRef>
                    <isList>true</isList>
                    <isInput>true</isInput>
                    <guid>a65c63d0-9bdc-44fb-82d8-8e8fd4ba69f1</guid>
                    <versionId>20e81df9-d083-4faa-9c97-bd6d8648d534</versionId>
                    <description isNull="true" />
                </parameterMapping>
                <parameterMapping name="returnType">
                    <lastModified isNull="true" />
                    <lastModifiedBy isNull="true" />
                    <parameterMappingId>2054.f47cd5ca-f7f3-4e3f-9568-3a7e43e5fb53</parameterMappingId>
                    <processParameterId>2055.7081e3db-2301-4308-b93d-61cf78b25816</processParameterId>
                    <parameterMappingParentId>3012.ac245f99-a3c7-4780-8bc0-6c54df4102e0</parameterMappingParentId>
                    <useDefault>false</useDefault>
                    <value>"NameValuePair"</value>
                    <classRef>/12.db884a3c-c533-44b7-bb2d-47bec8ad4022</classRef>
                    <isList>false</isList>
                    <isInput>true</isInput>
                    <guid>f5d4d2f4-4dfd-4ad3-88e0-ecc4a9ef3313</guid>
                    <versionId>5db6a912-11d8-4a10-a5a9-d5918efaa4b9</versionId>
                    <description isNull="true" />
                </parameterMapping>
                <parameterMapping name="dataSourceName">
                    <lastModified isNull="true" />
                    <lastModifiedBy isNull="true" />
                    <parameterMappingId>2054.b377eeda-92fb-4a58-aaef-ac2f506615c5</parameterMappingId>
                    <processParameterId>2055.a5856f85-7a86-4327-9481-b1df1c075ff9</processParameterId>
                    <parameterMappingParentId>3012.ac245f99-a3c7-4780-8bc0-6c54df4102e0</parameterMappingParentId>
                    <useDefault>false</useDefault>
                    <value>tw.local.jndiName</value>
                    <classRef>/12.db884a3c-c533-44b7-bb2d-47bec8ad4022</classRef>
                    <isList>false</isList>
                    <isInput>true</isInput>
                    <guid>7739909d-e93e-4980-b4d4-32b2a51abef6</guid>
                    <versionId>70ce99ed-0719-49ae-9568-d4763cbb1b9a</versionId>
                    <description isNull="true" />
                </parameterMapping>
                <parameterMapping name="sql">
                    <lastModified isNull="true" />
                    <lastModifiedBy isNull="true" />
                    <parameterMappingId>2054.e78d2130-f4aa-48ab-a178-dbe915d3fe4b</parameterMappingId>
                    <processParameterId>2055.e3bfe8f3-c801-4ef8-bb77-77156e3b0326</processParameterId>
                    <parameterMappingParentId>3012.ac245f99-a3c7-4780-8bc0-6c54df4102e0</parameterMappingParentId>
                    <useDefault>false</useDefault>
                    <value>tw.local.sqlStatement</value>
                    <classRef>/12.db884a3c-c533-44b7-bb2d-47bec8ad4022</classRef>
                    <isList>false</isList>
                    <isInput>true</isInput>
                    <guid>c2a27f41-3861-4b5e-92e8-ddb3dff84da2</guid>
                    <versionId>9c80510b-e1cd-4171-8316-0749d9422eef</versionId>
                    <description isNull="true" />
                </parameterMapping>
                <parameterMapping name="maxRows">
                    <lastModified isNull="true" />
                    <lastModifiedBy isNull="true" />
                    <parameterMappingId>2054.f7ae9ad1-5af6-4ed1-999d-35244179763c</parameterMappingId>
                    <processParameterId>2055.ec350cc0-a909-411a-b0c2-96e08b779c85</processParameterId>
                    <parameterMappingParentId>3012.ac245f99-a3c7-4780-8bc0-6c54df4102e0</parameterMappingParentId>
                    <useDefault>false</useDefault>
                    <value>tw.env.maxSQLQueryRowsReturned</value>
                    <classRef>/12.3fa0d7a0-828a-4d60-99cc-db5ed143fc2d</classRef>
                    <isList>false</isList>
                    <isInput>true</isInput>
                    <guid>5d23f20c-6638-442a-89ab-d7005a2bed8a</guid>
                    <versionId>d0885d30-f709-4fa9-b7cf-6b0beffddea5</versionId>
                    <description isNull="true" />
                </parameterMapping>
                <parameterMapping name="results">
                    <lastModified isNull="true" />
                    <lastModifiedBy isNull="true" />
                    <parameterMappingId>2054.5eaa9acf-f080-4f67-a7c6-b7ef78709378</parameterMappingId>
                    <processParameterId>2055.21cdb854-d222-4fc8-b991-17aef09de0c4</processParameterId>
                    <parameterMappingParentId>3012.ac245f99-a3c7-4780-8bc0-6c54df4102e0</parameterMappingParentId>
                    <useDefault>false</useDefault>
                    <value>tw.local.results</value>
                    <classRef>/12.c09c9b6e-aabd-4897-bef2-ed61db106297</classRef>
                    <isList>false</isList>
                    <isInput>false</isInput>
                    <guid>f3c3adb4-1697-4a3d-a896-96fb9f4e36f6</guid>
                    <versionId>dd267f6c-63f4-47a8-bcf6-02e4bca5af83</versionId>
                    <description isNull="true" />
                </parameterMapping>
            </TWComponent>
        </item>
        <item>
            <lastModified isNull="true" />
            <lastModifiedBy isNull="true" />
            <processItemId>2025.55c0f771-7c82-4b97-a069-b63a0390ce8c</processItemId>
            <processId>1.02cc1aee-431d-4aa0-87fc-b046b07cdbeb</processId>
            <name>End</name>
            <tWComponentName>ExitPoint</tWComponentName>
            <tWComponentId>3008.d46a7469-23fd-422b-8f6b-96e6a3177370</tWComponentId>
            <isLogEnabled>false</isLogEnabled>
            <isTraceEnabled>false</isTraceEnabled>
            <traceCategory isNull="true" />
            <traceLevel isNull="true" />
            <traceMessage isNull="true" />
            <traceSymbolTable isNull="true" />
            <isExecutionContextTraced>false</isExecutionContextTraced>
            <saveExecutionContext>true</saveExecutionContext>
            <documentation isNull="true" />
            <isErrorHandlerEnabled>false</isErrorHandlerEnabled>
            <errorHandlerItemId isNull="true" />
            <guid>guid:1df100aa714bb228:7f4ddbfc:163e4948e80:-761a</guid>
            <versionId>29839295-5b4a-43f1-ad89-2941eff54f50</versionId>
            <externalServiceRef isNull="true" />
            <externalServiceOp isNull="true" />
            <nodeColor isNull="true" />
            <layoutData x="649" y="79">
                <errorLink>
                    <controlPoints />
                    <showEndState>false</showEndState>
                    <showName>false</showName>
                </errorLink>
            </layoutData>
            <TWComponent>
                <lastModified isNull="true" />
                <lastModifiedBy isNull="true" />
                <exitPointId>3008.d46a7469-23fd-422b-8f6b-96e6a3177370</exitPointId>
                <haltProcess>false</haltProcess>
                <guid>0f090582-e6e0-4886-8b4e-96ce11793036</guid>
                <versionId>9ff5e78f-80f6-4488-93d8-08cb62d550cf</versionId>
            </TWComponent>
        </item>
        <item>
            <lastModified isNull="true" />
            <lastModifiedBy isNull="true" />
            <processItemId>2025.2abd430b-a057-4be0-96b1-638b80cb25ea</processItemId>
            <processId>1.02cc1aee-431d-4aa0-87fc-b046b07cdbeb</processId>
            <name>Define SQL</name>
            <tWComponentName>Script</tWComponentName>
            <tWComponentId>3011.1c5bc7bf-7790-4514-98bf-16cb861e532e</tWComponentId>
            <isLogEnabled>false</isLogEnabled>
            <isTraceEnabled>false</isTraceEnabled>
            <traceCategory isNull="true" />
            <traceLevel isNull="true" />
            <traceMessage isNull="true" />
            <traceSymbolTable isNull="true" />
            <isExecutionContextTraced>false</isExecutionContextTraced>
            <saveExecutionContext>false</saveExecutionContext>
            <documentation isNull="true" />
            <isErrorHandlerEnabled>false</isErrorHandlerEnabled>
            <errorHandlerItemId isNull="true" />
            <guid>guid:1df100aa714bb228:7f4ddbfc:163e4948e80:-761b</guid>
            <versionId>2f545989-9506-4908-b6e2-8ee7760d0d96</versionId>
            <externalServiceRef isNull="true" />
            <externalServiceOp isNull="true" />
            <nodeColor isNull="true" />
            <layoutData x="147" y="57">
                <errorLink>
                    <controlPoints />
                    <showEndState>false</showEndState>
                    <showName>false</showName>
                </errorLink>
            </layoutData>
            <TWComponent>
                <lastModified isNull="true" />
                <lastModifiedBy isNull="true" />
                <scriptId>3011.1c5bc7bf-7790-4514-98bf-16cb861e532e</scriptId>
                <scriptTypeId>128</scriptTypeId>
                <isActive>true</isActive>
                <script>tw.local.sqlStatement
select distinct MIME_TYPE as name, MIME_TYPE as value from LSW_MANAGED_ASSET where MIME_TYPE is not null order by MIME_TYPE</script>
                <isRule>false</isRule>
                <guid>fdea7323-8773-4782-83f4-e747dc7faf90</guid>
                <versionId>eb1314de-c2b5-402b-b453-6032aef7c667</versionId>
            </TWComponent>
        </item>
        <startingProcessItemId>2025.2abd430b-a057-4be0-96b1-638b80cb25ea</startingProcessItemId>
        <errorHandlerItemId isNull="true" />
        <layoutData noConversion="true">
            <errorLink>
                <controlPoints />
                <showEndState>false</showEndState>
                <showName>false</showName>
            </errorLink>
        </layoutData>
        <startPoint>
            <layoutData x="25" y="80">
                <errorLink>
                    <controlPoints />
                    <showEndState>false</showEndState>
                    <showName>false</showName>
                </errorLink>
            </layoutData>
        </startPoint>
        <startLink>
            <fromPort locationId="rightCenter" portType="1" />
            <toPort locationId="leftCenter" portType="2" />
            <layoutData>
                <controlPoints />
                <showEndState>false</showEndState>
                <showName>false</showName>
            </layoutData>
        </startLink>
        <bpmn2Model>
            <ns17:definitions xmlns:ns17="http://www.omg.org/spec/BPMN/20100524/MODEL" xmlns:ns2="http://www.ibm.com/xmlns/prod/bpm/bpmn/ext/process/case" xmlns:ns3="http://www.ibm.com/xmlns/prod/bpm/bpmn/ext/process" xmlns:ns4="http://www.ibm.com/xmlns/prod/bpm/bpmn/ext/process/wle" xmlns:ns5="http://www.ibm.com/bpm/Extensions" xmlns:ns6="http://www.ibm.com/xmlns/prod/bpm/uca" xmlns:ns7="http://www.ibm.com/xmlns/prod/bpm/bpmn/ext/trackinggroup" xmlns:ns8="http://www.ibm.com/xmlns/prod/bpm/bpmn/ext/team" xmlns:ns9="http://www.ibm.com/xmlns/bpmnx/20100524/v1/BusinessVocabulary" xmlns:ns10="http://www.omg.org/spec/DD/20100524/DI" xmlns:ns11="http://www.omg.org/spec/DD/20100524/DC" xmlns:ns12="http://www.omg.org/spec/BPMN/20100524/BPMNDI" xmlns:ns13="http://www.ibm.com/xmlns/prod/bpm/graph" xmlns:ns14="http://www.ibm.com/xmlns/prod/bpm/bpmn/ext/process/auth" xmlns:ns15="http://www.ibm.com/xmlns/prod/bpm/bpmn/ext/extservice" xmlns:ns16="http://www.ibm.com/xmlns/links" xmlns:ns18="http://www.ibm.com/bpm/CoachDesignerNG" xmlns:ns19="http://www.ibm.com/xmlns/tagging" xmlns:ns20="http://www.ibm.com/bpm/uitheme" xmlns:ns21="http://www.ibm.com/bpm/coachview" targetNamespace="" expressionLanguage="http://www.ibm.com/xmlns/prod/bpm/expression-lang/javascript" typeLanguage="http://www.w3.org/2001/XMLSchema">
                
                
                
                
                <ns17:process name="Get MIME Types NV Pair" id="1.02cc1aee-431d-4aa0-87fc-b046b07cdbeb" ns3:executionMode="microflow">
                    
                    
                    
                    
                    <ns17:documentation textFormat="text/plain" />
                    
                    
                    
                    
                    <ns17:extensionElements>
                        
                        
                        
                        
                        <ns3:sboSyncEnabled>true</ns3:sboSyncEnabled>
                        
                        
                        
                        
                        <ns3:isAjaxExposed>true</ns3:isAjaxExposed>
                        
                        
                        
                        
                        <ns3:isSecured>true</ns3:isSecured>
                        
                        
                        
                        
                        <ns3:cachingType>true</ns3:cachingType>
                        
                        
                        
                        
                        <ns3:cacheLength>43200</ns3:cacheLength>
                        
                        
                    
                    
                    </ns17:extensionElements>
                    
                    
                    
                    
                    <ns17:ioSpecification>
                        
                        
                        
                        
                        <ns17:dataInput name="data" itemSubjectRef="itm.12.c09c9b6e-aabd-4897-bef2-ed61db106297" isCollection="false" id="2055.144c3294-0c32-4609-a4df-e78e0bb91187" />
                        
                        
                        
                        
                        <ns17:dataOutput name="results" itemSubjectRef="itm.12.c09c9b6e-aabd-4897-bef2-ed61db106297" isCollection="true" id="2055.ab426bca-cbe8-41d0-ac77-9812fb594171" />
                        
                        
                        
                        
                        <ns17:inputSet>
                            
                            
                            
                            
                            <ns17:dataInputRefs>2055.144c3294-0c32-4609-a4df-e78e0bb91187</ns17:dataInputRefs>
                            
                            
                        
                        
                        </ns17:inputSet>
                        
                        
                        
                        
                        <ns17:outputSet>
                            
                            
                            
                            
                            <ns17:dataOutputRefs>2055.ab426bca-cbe8-41d0-ac77-9812fb594171</ns17:dataOutputRefs>
                            
                            
                        
                        
                        </ns17:outputSet>
                        
                        
                    
                    
                    </ns17:ioSpecification>
                    
                    
                    
                    
                    <ns17:laneSet id="16ec2d95-29c8-4231-b07f-642c988651ff">
                        
                        
                        
                        
                        <ns17:lane name="System" partitionElementRef="24.6fd38d02-81cf-48ab-bd42-8ff4c0a1628b" id="66439f72-f08e-43c7-abcf-42fc7ab1a54b" ns4:isSystemLane="true">
                            
                            
                            
                            
                            <ns17:extensionElements>
                                
                                
                                
                                
                                <ns13:nodeVisualInfo x="0" y="0" width="3000" height="500" color="#F8F8F8" />
                                
                                
                            
                            
                            </ns17:extensionElements>
                            
                            
                            
                            
                            <ns17:flowNodeRef>773b444a-fd05-4ffe-a0d6-34bfafac5166</ns17:flowNodeRef>
                            
                            
                            
                            
                            <ns17:flowNodeRef>55c0f771-7c82-4b97-a069-b63a0390ce8c</ns17:flowNodeRef>
                            
                            
                            
                            
                            <ns17:flowNodeRef>2abd430b-a057-4be0-96b1-638b80cb25ea</ns17:flowNodeRef>
                            
                            
                            
                            
                            <ns17:flowNodeRef>7e5b4f4f-7e16-4708-981d-1f94533cd4ee</ns17:flowNodeRef>
                            
                            
                        
                        
                        </ns17:lane>
                        
                        
                    
                    
                    </ns17:laneSet>
                    
                    
                    
                    
                    <ns17:startEvent isInterrupting="false" parallelMultiple="false" name="Start" id="773b444a-fd05-4ffe-a0d6-34bfafac5166">
                        
                        
                        
                        
                        <ns17:extensionElements>
                            
                            
                            
                            
                            <ns13:nodeVisualInfo x="25" y="80" width="24" height="24" color="#F8F8F8" />
                            
                            
                        
                        
                        </ns17:extensionElements>
                        
                        
                        
                        
                        <ns17:outgoing>2027.a2be8670-3af3-4fba-890b-9dcc63bd3a9e</ns17:outgoing>
                        
                        
                    
                    
                    </ns17:startEvent>
                    
                    
                    
                    
                    <ns17:endEvent name="End" id="55c0f771-7c82-4b97-a069-b63a0390ce8c">
                        
                        
                        
                        
                        <ns17:extensionElements>
                            
                            
                            
                            
                            <ns13:nodeVisualInfo x="649" y="79" width="24" height="24" color="#F8F8F8" />
                            
                            
                            
                            
                            <ns4:saveExecutionContext>true</ns4:saveExecutionContext>
                            
                            
                            
                            
                            <ns3:endStateId>guid:1df100aa714bb228:7f4ddbfc:163e4948e80:-761a</ns3:endStateId>
                            
                            
                        
                        
                        </ns17:extensionElements>
                        
                        
                        
                        
                        <ns17:incoming>dc0fa123-e737-47dc-a2b9-6ad02c61d86c</ns17:incoming>
                        
                        
                    
                    
                    </ns17:endEvent>
                    
                    
                    
                    
                    <ns17:sequenceFlow sourceRef="773b444a-fd05-4ffe-a0d6-34bfafac5166" targetRef="2abd430b-a057-4be0-96b1-638b80cb25ea" name="To End" id="2027.a2be8670-3af3-4fba-890b-9dcc63bd3a9e">
                        
                        
                        
                        
                        <ns17:extensionElements>
                            
                            
                            
                            
                            <ns13:linkVisualInfo>
                                
                                
                                
                                
                                <ns13:sourcePortLocation>rightCenter</ns13:sourcePortLocation>
                                
                                
                                
                                
                                <ns13:targetPortLocation>leftCenter</ns13:targetPortLocation>
                                
                                
                                
                                
                                <ns13:showLabel>false</ns13:showLabel>
                                
                                
                                
                                
                                <ns13:showCoachControlLabel>false</ns13:showCoachControlLabel>
                                
                                
                                
                                
                                <ns13:labelPosition>0.0</ns13:labelPosition>
                                
                                
                                
                                
                                <ns13:saveExecutionContext>false</ns13:saveExecutionContext>
                                
                                
                            
                            
                            </ns13:linkVisualInfo>
                            
                            
                        
                        
                        </ns17:extensionElements>
                        
                        
                    
                    
                    </ns17:sequenceFlow>
                    
                    
                    
                    
                    <ns17:scriptTask scriptFormat="text/plain" name="Define SQL" id="2abd430b-a057-4be0-96b1-638b80cb25ea">
                        
                        
                        
                        
                        <ns17:extensionElements>
                            
                            
                            
                            
                            <ns13:nodeVisualInfo x="147" y="57" width="95" height="70" />
                            
                            
                        
                        
                        </ns17:extensionElements>
                        
                        
                        
                        
                        <ns17:incoming>2027.a2be8670-3af3-4fba-890b-9dcc63bd3a9e</ns17:incoming>
                        
                        
                        
                        
                        <ns17:outgoing>1605e0f2-0666-4bc4-8e38-87640845267b</ns17:outgoing>
                        
                        
                        
                        
                        <ns17:script>tw.local.sqlStatement
select distinct MIME_TYPE as name, MIME_TYPE as value from LSW_MANAGED_ASSET where MIME_TYPE is not null order by MIME_TYPE</ns17:script>
                        
                        
                    
                    
                    </ns17:scriptTask>
                    
                    
                    
                    
                    <ns17:callActivity calledElement="1.8ca80af0-a727-4b90-9e04-21b32cd0c65c" name="SQL Execute Statement" id="7e5b4f4f-7e16-4708-981d-1f94533cd4ee">
                        
                        
                        
                        
                        <ns17:extensionElements>
                            
                            
                            
                            
                            <ns13:nodeVisualInfo x="330" y="56" width="95" height="70" />
                            
                            
                            
                            
                            <ns4:activityType>CalledProcess</ns4:activityType>
                            
                            
                        
                        
                        </ns17:extensionElements>
                        
                        
                        
                        
                        <ns17:incoming>1605e0f2-0666-4bc4-8e38-87640845267b</ns17:incoming>
                        
                        
                        
                        
                        <ns17:outgoing>dc0fa123-e737-47dc-a2b9-6ad02c61d86c</ns17:outgoing>
                        
                        
                        
                        
                        <ns17:dataInputAssociation>
                            
                            
                            
                            
                            <ns17:targetRef>2055.e3bfe8f3-c801-4ef8-bb77-77156e3b0326</ns17:targetRef>
                            
                            
                            
                            
                            <ns17:assignment>
                                
                                
                                
                                
                                <ns17:from xmlns:xsi="http://www.w3.org/2001/XMLSchema-instance" xsi:type="ns17:tFormalExpression" evaluatesToTypeRef="itm.12.db884a3c-c533-44b7-bb2d-47bec8ad4022">tw.local.sqlStatement</ns17:from>
                                
                                
                            
                            
                            </ns17:assignment>
                            
                            
                        
                        
                        </ns17:dataInputAssociation>
                        
                        
                        
                        
                        <ns17:dataInputAssociation>
                            
                            
                            
                            
                            <ns17:targetRef>2055.8b3c4f58-67b5-49b0-8df4-bdb407fbe076</ns17:targetRef>
                            
                            
                            
                            
                            <ns17:assignment>
                                
                                
                                
                                
                                <ns17:from xmlns:xsi="http://www.w3.org/2001/XMLSchema-instance" xsi:type="ns17:tFormalExpression" evaluatesToTypeRef="itm.12.f453f500-ca4e-4264-a371-72c1892e8b7c">tw.local.sqlParameters</ns17:from>
                                
                                
                            
                            
                            </ns17:assignment>
                            
                            
                        
                        
                        </ns17:dataInputAssociation>
                        
                        
                        
                        
                        <ns17:dataInputAssociation>
                            
                            
                            
                            
                            <ns17:targetRef>2055.a5856f85-7a86-4327-9481-b1df1c075ff9</ns17:targetRef>
                            
                            
                            
                            
                            <ns17:assignment>
                                
                                
                                
                                
                                <ns17:from xmlns:xsi="http://www.w3.org/2001/XMLSchema-instance" xsi:type="ns17:tFormalExpression" evaluatesToTypeRef="itm.12.db884a3c-c533-44b7-bb2d-47bec8ad4022">tw.local.jndiName</ns17:from>
                                
                                
                            
                            
                            </ns17:assignment>
                            
                            
                        
                        
                        </ns17:dataInputAssociation>
                        
                        
                        
                        
                        <ns17:dataInputAssociation>
                            
                            
                            
                            
                            <ns17:targetRef>2055.ec350cc0-a909-411a-b0c2-96e08b779c85</ns17:targetRef>
                            
                            
                            
                            
                            <ns17:assignment>
                                
                                
                                
                                
                                <ns17:from xmlns:xsi="http://www.w3.org/2001/XMLSchema-instance" xsi:type="ns17:tFormalExpression" evaluatesToTypeRef="itm.12.c09c9b6e-aabd-4897-bef2-ed61db106297">tw.env.maxSQLQueryRowsReturned</ns17:from>
                                
                                
                            
                            
                            </ns17:assignment>
                            
                            
                        
                        
                        </ns17:dataInputAssociation>
                        
                        
                        
                        
                        <ns17:dataInputAssociation>
                            
                            
                            
                            
                            <ns17:targetRef>2055.7081e3db-2301-4308-b93d-61cf78b25816</ns17:targetRef>
                            
                            
                            
                            
                            <ns17:assignment>
                                
                                
                                
                                
                                <ns17:from xmlns:xsi="http://www.w3.org/2001/XMLSchema-instance" xsi:type="ns17:tFormalExpression" evaluatesToTypeRef="itm.12.db884a3c-c533-44b7-bb2d-47bec8ad4022">"NameValuePair"</ns17:from>
                                
                                
                            
                            
                            </ns17:assignment>
                            
                            
                        
                        
                        </ns17:dataInputAssociation>
                        
                        
                        
                        
                        <ns17:dataOutputAssociation>
                            
                            
                            
                            
                            <ns17:sourceRef>2055.21cdb854-d222-4fc8-b991-17aef09de0c4</ns17:sourceRef>
                            
                            
                            
                            
                            <ns17:assignment>
                                
                                
                                
                                
                                <ns17:to xmlns:xsi="http://www.w3.org/2001/XMLSchema-instance" xsi:type="ns17:tFormalExpression" evaluatesToTypeRef="itm.12.c09c9b6e-aabd-4897-bef2-ed61db106297">tw.local.results</ns17:to>
                                
                                
                            
                            
                            </ns17:assignment>
                            
                            
                        
                        
                        </ns17:dataOutputAssociation>
                        
                        
                    
                    
                    </ns17:callActivity>
                    
                    
                    
                    
                    <ns17:sequenceFlow sourceRef="2abd430b-a057-4be0-96b1-638b80cb25ea" targetRef="7e5b4f4f-7e16-4708-981d-1f94533cd4ee" name="To SQL Execute Statement" id="1605e0f2-0666-4bc4-8e38-87640845267b">
                        
                        
                        
                        
                        <ns17:extensionElements>
                            
                            
                            
                            
                            <ns13:linkVisualInfo>
                                
                                
                                
                                
                                <ns13:sourcePortLocation>rightCenter</ns13:sourcePortLocation>
                                
                                
                                
                                
                                <ns13:targetPortLocation>leftCenter</ns13:targetPortLocation>
                                
                                
                                
                                
                                <ns13:showLabel>false</ns13:showLabel>
                                
                                
                                
                                
                                <ns13:showCoachControlLabel>false</ns13:showCoachControlLabel>
                                
                                
                                
                                
                                <ns13:labelPosition>0.0</ns13:labelPosition>
                                
                                
                                
                                
                                <ns13:saveExecutionContext>false</ns13:saveExecutionContext>
                                
                                
                            
                            
                            </ns13:linkVisualInfo>
                            
                            
                        
                        
                        </ns17:extensionElements>
                        
                        
                    
                    
                    </ns17:sequenceFlow>
                    
                    
                    
                    
                    <ns17:sequenceFlow sourceRef="7e5b4f4f-7e16-4708-981d-1f94533cd4ee" targetRef="55c0f771-7c82-4b97-a069-b63a0390ce8c" name="To End" id="dc0fa123-e737-47dc-a2b9-6ad02c61d86c">
                        
                        
                        
                        
                        <ns17:extensionElements>
                            
                            
                            
                            
                            <ns3:sequenceFlowImplementation sboSyncEnabled="true" />
                            
                            
                            
                            
                            <ns13:linkVisualInfo>
                                
                                
                                
                                
                                <ns13:sourcePortLocation>rightCenter</ns13:sourcePortLocation>
                                
                                
                                
                                
                                <ns13:targetPortLocation>leftCenter</ns13:targetPortLocation>
                                
                                
                                
                                
                                <ns13:showLabel>false</ns13:showLabel>
                                
                                
                                
                                
                                <ns13:showCoachControlLabel>false</ns13:showCoachControlLabel>
                                
                                
                                
                                
                                <ns13:labelPosition>0.0</ns13:labelPosition>
                                
                                
                                
                                
                                <ns13:saveExecutionContext>true</ns13:saveExecutionContext>
                                
                                
                            
                            
                            </ns13:linkVisualInfo>
                            
                            
                            
                            
                            <ns3:endStateId>guid:d7766b7587753602:-9d2f0f9:11586bfc263:-7f6f</ns3:endStateId>
                            
                            
                        
                        
                        </ns17:extensionElements>
                        
                        
                    
                    
                    </ns17:sequenceFlow>
                    
                    
                    
                    
                    <ns17:dataObject itemSubjectRef="itm.12.ae08caf5-4a15-4f12-a99e-d44923fd7975" isCollection="true" name="InstanceSummary" id="2056.98677004-e7d5-435f-941a-2a42e21d26fa">
                        
                        
                        
                        
                        <ns17:extensionElements>
                            
                            
                            
                            
                            <ns3:defaultValue useDefault="true">var autoObject = new tw.object.listOf.AppNameValue();
autoObject[0] = new tw.object.AppNameValue();
autoObject</ns3:defaultValue>
                            
                            
                        
                        
                        </ns17:extensionElements>
                        
                        
                    
                    
                    </ns17:dataObject>
                    
                    
                    
                    
                    <ns17:dataObject itemSubjectRef="itm.12.f453f500-ca4e-4264-a371-72c1892e8b7c" isCollection="true" name="sqlParameters" id="2056.129df22a-9b8a-4df4-947e-ec4bfe936372">
                        
                        
                        
                        
                        <ns17:extensionElements>
                            
                            
                            
                            
                            <ns3:defaultValue useDefault="true">var autoObject = new tw.object.listOf.toolkit.TWSYS.SQLParameter();
autoObject</ns3:defaultValue>
                            
                            
                        
                        
                        </ns17:extensionElements>
                        
                        
                    
                    
                    </ns17:dataObject>
                    
                    
                    
                    
                    <ns17:dataObject itemSubjectRef="itm.12.db884a3c-c533-44b7-bb2d-47bec8ad4022" isCollection="false" name="jndiName" id="2056.70eaf1a4-9974-4a7c-af16-c40c689b93b8">
                        
                        
                        
                        
                        <ns17:extensionElements>
                            
                            
                            
                            
                            <ns3:defaultValue useDefault="true">String(tw.env.ProcessServerDBJNDINAME)	</ns3:defaultValue>
                            
                            
                        
                        
                        </ns17:extensionElements>
                        
                        
                    
                    
                    </ns17:dataObject>
                    
                    
                    
                    
                    <ns17:dataObject itemSubjectRef="itm.12.d2e5a15a-ea53-4793-9e93-29af5bd80b13" isCollection="true" name="instancesStatuses" id="2056.bebb2dae-a3f9-484a-890e-f7d6d3808410">
                        
                        
                        
                        
                        <ns17:extensionElements>
                            
                            
                            
                            
                            <ns3:defaultValue useDefault="true">var autoObject = new tw.object.listOf.toolkit.TWSYS.NameValuePair();
autoObject[0] = new tw.object.toolkit.TWSYS.NameValuePair();
autoObject[0].name = "Active";
autoObject[0].value = "1";
autoObject[1] = new tw.object.toolkit.TWSYS.NameValuePair();&#xD;
autoObject[1].name = "Completed";&#xD;
autoObject[1].value = "2";&#xD;
autoObject[2] = new tw.object.toolkit.TWSYS.NameValuePair();&#xD;
autoObject[2].name = "Failed";&#xD;
autoObject[2].value = "3";&#xD;
autoObject[3] = new tw.object.toolkit.TWSYS.NameValuePair();&#xD;
autoObject[3].name = "Terminated";&#xD;
autoObject[3].value = "4";&#xD;
autoObject[4] = new tw.object.toolkit.TWSYS.NameValuePair();&#xD;
autoObject[4].name = "Did_not_Start";&#xD;
autoObject[4].value = "5";&#xD;
autoObject[5] = new tw.object.toolkit.TWSYS.NameValuePair();&#xD;
autoObject[5].name = "Suspended";&#xD;
autoObject[5].value = "6";&#xD;
autoObject&#xD;
&#xD;
/*&#xD;
1 - The Process instance is currently active &#xD;
2 - The Process instance has completed or Finished &#xD;
3 - The Process instance has failed due error in execution&#xD;
4 - The Process instance has been terminated(abort) &#xD;
5 - The Process instance could not Start &#xD;
6 - The Process instance was suspended &#xD;
*/</ns3:defaultValue>
                            
                            
                        
                        
                        </ns17:extensionElements>
                        
                        
                    
                    
                    </ns17:dataObject>
                    
                    
                    
                    
                    <ns17:dataObject itemSubjectRef="itm.12.db884a3c-c533-44b7-bb2d-47bec8ad4022" isCollection="false" name="sqlStatement" id="2056.404f732d-baa5-4e9c-abd9-a1c517889552">
                        
                        
                        
                        
                        <ns17:extensionElements>
                            
                            
                            
                            
                            <ns3:defaultValue useDefault="true">""</ns3:defaultValue>
                            
                            
                        
                        
                        </ns17:extensionElements>
                        
                        
                    
                    
                    </ns17:dataObject>
                    
                    
                    
                    
                    <ns17:dataObject itemSubjectRef="itm.12.63a604e8-e026-4605-aae1-272b67822cc7" isCollection="true" name="dataSeriesP" id="2056.fddf5aa2-cc79-40f8-80c6-c288a0b4f39f">
                        
                        
                        
                        
                        <ns17:extensionElements>
                            
                            
                            
                            
                            <ns3:defaultValue useDefault="true">var autoObject = new tw.object.listOf.toolkit.SYSBPMUI.DataSeries();
autoObject[0] = new tw.object.toolkit.SYSBPMUI.DataSeries();
autoObject[0].seriesName = "All Applications";
autoObject[0].dataPoints = new tw.object.listOf.toolkit.SYSBPMUI.DataPoint();
autoObject[0].dataPoints[0] = new tw.object.toolkit.SYSBPMUI.DataPoint();
autoObject[0].dataPoints[0].value = 0.0;
autoObject[0].dataPoints[0].label = "";
autoObject</ns3:defaultValue>
                            
                            
                        
                        
                        </ns17:extensionElements>
                        
                        
                    
                    
                    </ns17:dataObject>
                    
                    
                
                
                </ns17:process>
                
                
            
            
            </ns17:definitions>
        </bpmn2Model>
        <link name="To End">
            <lastModified isNull="true" />
            <lastModifiedBy isNull="true" />
            <processLinkId>2027.134927d4-85c5-4da7-aeca-a8291d1463e2</processLinkId>
            <processId>1.02cc1aee-431d-4aa0-87fc-b046b07cdbeb</processId>
            <description isNull="true" />
            <fromProcessItemId>2025.7e5b4f4f-7e16-4708-981d-1f94533cd4ee</fromProcessItemId>
            <endStateId>guid:d7766b7587753602:-9d2f0f9:11586bfc263:-7f6f</endStateId>
            <toProcessItemId>2025.55c0f771-7c82-4b97-a069-b63a0390ce8c</toProcessItemId>
            <guid>68c51f22-2c7a-41ab-8caa-df53f8917abe</guid>
            <versionId>f13dbcf4-f234-47df-997d-a11d60759dd4</versionId>
            <layoutData>
                <controlPoints />
                <showEndState>false</showEndState>
                <showName>false</showName>
            </layoutData>
            <fromItemPort locationId="rightCenter" portType="1" />
            <toItemPort locationId="leftCenter" portType="2" />
            <fromProcessItemId>2025.7e5b4f4f-7e16-4708-981d-1f94533cd4ee</fromProcessItemId>
            <toProcessItemId>2025.55c0f771-7c82-4b97-a069-b63a0390ce8c</toProcessItemId>
        </link>
        <link name="To SQL Execute Statement">
            <lastModified isNull="true" />
            <lastModifiedBy isNull="true" />
            <processLinkId>2027.23d0a005-e70a-4068-97aa-2d95d7ca3ca7</processLinkId>
            <processId>1.02cc1aee-431d-4aa0-87fc-b046b07cdbeb</processId>
            <description isNull="true" />
            <fromProcessItemId>2025.2abd430b-a057-4be0-96b1-638b80cb25ea</fromProcessItemId>
            <endStateId>Out</endStateId>
            <toProcessItemId>2025.7e5b4f4f-7e16-4708-981d-1f94533cd4ee</toProcessItemId>
            <guid>82f68cba-835f-4775-a16f-396ae83f24c5</guid>
            <versionId>f7c22ba2-4416-402f-abf5-28cf4db546da</versionId>
            <layoutData>
                <controlPoints />
                <showEndState>false</showEndState>
                <showName>false</showName>
            </layoutData>
            <fromItemPort locationId="rightCenter" portType="1" />
            <toItemPort locationId="leftCenter" portType="2" />
            <fromProcessItemId>2025.2abd430b-a057-4be0-96b1-638b80cb25ea</fromProcessItemId>
            <toProcessItemId>2025.7e5b4f4f-7e16-4708-981d-1f94533cd4ee</toProcessItemId>
        </link>
    </process>
</teamworks>

